{
    "latency": 91.38228289361703,
    "energy": 42480826350877.8,
    "energy_rsts": {
        "DRAM": 0.0,
        "L3": 21047882775724.555,
        "reg_file": 0.0,
        "PE": 21432943575153.246,
        "total": 42480826350877.8
    },
    "tl_rsts": {
        "SM": {
            "tl_rst": {
                "comp_latency": 9.138228289361702,
                "mem_latency": 0.0,
                "traffic": 0,
                "energy": 7513512708.41,
                "traffic_energy": 6718253323787.305,
                "traffic_energy_foreach": {
                    "DRAM": 0.0,
                    "L3": 6718253323787.305,
                    "reg_file": 0.0,
                    "traffic": {
                        "DRAM": {
                            "read": 0.0,
                            "write": 0.0,
                            "update": 0,
                            "leak": 0
                        },
                        "L3": {
                            "read": 536870912.0,
                            "write": 32768.0,
                            "update": 0,
                            "leak": 0
                        },
                        "reg_file_2d": {
                            "read": 0,
                            "write": 0,
                            "update": 0,
                            "leak": 0
                        },
                        "reg_file_1d": {
                            "read": 0.0,
                            "write": 0.0,
                            "update": 0,
                            "leak": 0
                        }
                    }
                },
                "mac_instances": 256,
                "mac_utilized_instances": 16
            },
            "factors": {
                "DRAM": {
                    "B": 64,
                    "H": 8,
                    "P": 16384,
                    "M": 1,
                    "N": 1
                },
                "L3": {
                    "B": 1,
                    "H": 1,
                    "P": 1,
                    "M": 1024,
                    "N": 1
                },
                "PE": {
                    "B": 1,
                    "H": 1,
                    "P": 1,
                    "M": 1,
                    "N": 16
                },
                "reg_file": {
                    "B": 1,
                    "H": 1,
                    "P": 1,
                    "M": 1,
                    "N": 1
                }
            }
        },
        "SN": {
            "tl_rst": {
                "comp_latency": 63.96759802553191,
                "mem_latency": 0.0,
                "traffic": 0,
                "energy": 7513512708.41,
                "traffic_energy": 15174648200687.387,
                "traffic_energy_foreach": {
                    "DRAM": 0.0,
                    "L3": 15174648200687.387,
                    "reg_file": 0.0,
                    "traffic": {
                        "DRAM": {
                            "read": 0.0,
                            "write": 0.0,
                            "update": 0,
                            "leak": 0
                        },
                        "L3": {
                            "read": 536903680.0,
                            "write": 536870912.0,
                            "update": 0,
                            "leak": 0
                        },
                        "reg_file_2d": {
                            "read": 0,
                            "write": 0,
                            "update": 0,
                            "leak": 0
                        },
                        "reg_file_1d": {
                            "read": 0.0,
                            "write": 0.0,
                            "update": 0,
                            "leak": 0
                        }
                    }
                },
                "mac_instances": 256,
                "mac_utilized_instances": 16
            },
            "factors": {
                "DRAM": {
                    "B": 64,
                    "H": 8,
                    "M": 1,
                    "N": 1,
                    "P": 16384
                },
                "L3": {
                    "B": 1,
                    "H": 1,
                    "M": 1024,
                    "N": 1,
                    "P": 1
                },
                "PE": {
                    "B": 1,
                    "H": 1,
                    "M": 1,
                    "N": 16,
                    "P": 1
                },
                "reg_file": {
                    "B": 1,
                    "H": 1,
                    "M": 1,
                    "N": 1,
                    "P": 1
                }
            }
        },
        "SD": {
            "tl_rst": {
                "comp_latency": 9.138228289361702,
                "mem_latency": 0.0,
                "traffic": 0,
                "energy": 7513512708.41,
                "traffic_energy": 6718253323787.305,
                "traffic_energy_foreach": {
                    "DRAM": 0.0,
                    "L3": 6718253323787.305,
                    "reg_file": 0.0,
                    "traffic": {
                        "DRAM": {
                            "read": 0.0,
                            "write": 0.0,
                            "update": 0,
                            "leak": 0
                        },
                        "L3": {
                            "read": 536870912.0,
                            "write": 32768.0,
                            "update": 0,
                            "leak": 0
                        },
                        "reg_file_2d": {
                            "read": 0,
                            "write": 0,
                            "update": 0,
                            "leak": 0
                        },
                        "reg_file_1d": {
                            "read": 0.0,
                            "write": 0.0,
                            "update": 0,
                            "leak": 0
                        }
                    }
                },
                "mac_instances": 256,
                "mac_utilized_instances": 16
            },
            "factors": {
                "DRAM": {
                    "B": 64,
                    "H": 8,
                    "P": 16384,
                    "M": 1,
                    "N": 1
                },
                "L3": {
                    "B": 1,
                    "H": 1,
                    "P": 1,
                    "M": 1024,
                    "N": 1
                },
                "PE": {
                    "B": 1,
                    "H": 1,
                    "P": 1,
                    "M": 1,
                    "N": 16
                },
                "reg_file": {
                    "B": 1,
                    "H": 1,
                    "P": 1,
                    "M": 1,
                    "N": 1
                }
            }
        },
        "SA": {
            "tl_rst": {
                "comp_latency": 9.138228289361702,
                "mem_latency": 0.0,
                "traffic": 0,
                "energy": 7513512708.41,
                "traffic_energy": 15174648200687.387,
                "traffic_energy_foreach": {
                    "DRAM": 0.0,
                    "L3": 15174648200687.387,
                    "reg_file": 0.0,
                    "traffic": {
                        "DRAM": {
                            "read": 0.0,
                            "write": 0.0,
                            "update": 0,
                            "leak": 0
                        },
                        "L3": {
                            "read": 536903680.0,
                            "write": 536870912.0,
                            "update": 0,
                            "leak": 0
                        },
                        "reg_file_2d": {
                            "read": 0,
                            "write": 0,
                            "update": 0,
                            "leak": 0
                        },
                        "reg_file_1d": {
                            "read": 0.0,
                            "write": 0.0,
                            "update": 0,
                            "leak": 0
                        }
                    }
                },
                "mac_instances": 256,
                "mac_utilized_instances": 16
            },
            "factors": {
                "DRAM": {
                    "B": 64,
                    "H": 8,
                    "M": 1,
                    "N": 1,
                    "P": 16384
                },
                "L3": {
                    "B": 1,
                    "H": 1,
                    "M": 1024,
                    "N": 1,
                    "P": 1
                },
                "PE": {
                    "B": 1,
                    "H": 1,
                    "M": 1,
                    "N": 16,
                    "P": 1
                },
                "reg_file": {
                    "B": 1,
                    "H": 1,
                    "M": 1,
                    "N": 1,
                    "P": 1
                }
            }
        }
    }
}