{
    "latency": 9.147152340425531,
    "energy": 47753327960951.516,
    "energy_rsts": {
        "DRAM": 131022028.8,
        "L3": 9875459093433.182,
        "reg_file": 132542968715.6736,
        "PE": 37745194876773.86,
        "total": 47753327960951.516
    },
    "tl_rsts": {
        "FFN": {
            "tl_rst": {
                "comp_latency": 4.569114144680851,
                "mem_latency": 6.52313232421875e-05,
                "traffic": 2101248,
                "energy": 60108101667.26,
                "traffic_energy": 8572022677980.902,
                "traffic_energy_foreach": {
                    "DRAM": 65558937.6,
                    "L3": 8509719457838.331,
                    "reg_file": 62237661204.97151,
                    "traffic": {
                        "DRAM": {
                            "read": 262656.0,
                            "write": 0.0,
                            "update": 0,
                            "leak": 0
                        },
                        "L3": {
                            "read": 595599360.0,
                            "write": 67112968.0,
                            "update": 0,
                            "leak": 0
                        },
                        "reg_file_2d": {
                            "read": 17171480576.0,
                            "write": 12943753216.0,
                            "update": 0,
                            "leak": 0
                        },
                        "reg_file_1d": {
                            "read": 0,
                            "write": 0,
                            "update": 0,
                            "leak": 0
                        }
                    }
                },
                "mac_instances": 256,
                "mac_utilized_instances": 256
            },
            "factors": {
                "DRAM": {
                    "B": 64,
                    "S": 4,
                    "P": 16,
                    "F": 1,
                    "H": 1
                },
                "L3": {
                    "B": 1,
                    "S": 32,
                    "P": 64,
                    "F": 64,
                    "H": 8
                },
                "PE": {
                    "B": 1,
                    "S": 1,
                    "P": 16,
                    "F": 1,
                    "H": 1
                },
                "PE_col": {
                    "B": 1,
                    "S": 16,
                    "P": 1,
                    "F": 1,
                    "H": 1
                },
                "reg_file": {
                    "B": 1,
                    "S": 1,
                    "P": 1,
                    "F": 1,
                    "H": 1
                }
            }
        },
        "AR": {
            "tl_rst": {
                "comp_latency": 0.008924051063829787,
                "mem_latency": 0.0,
                "traffic": 0,
                "energy": 117398636.07,
                "traffic_energy": 237097471602.32755,
                "traffic_energy_foreach": {
                    "DRAM": 0.0,
                    "L3": 237097471602.32755,
                    "reg_file": 0.0,
                    "traffic": {
                        "DRAM": {
                            "read": 0.0,
                            "write": 0.0,
                            "update": 0,
                            "leak": 0
                        },
                        "L3": {
                            "read": 8388608.0,
                            "write": 8388608.0,
                            "update": 0,
                            "leak": 0
                        },
                        "reg_file_2d": {
                            "read": 0,
                            "write": 0,
                            "update": 0,
                            "leak": 0
                        },
                        "reg_file_1d": {
                            "read": 0.0,
                            "write": 0.0,
                            "update": 0,
                            "leak": 0
                        }
                    }
                },
                "mac_instances": 256,
                "mac_utilized_instances": 256
            },
            "factors": {
                "DRAM": {
                    "B": 64,
                    "S": 4,
                    "P": 16
                },
                "L3": {
                    "B": 1,
                    "S": 32,
                    "P": 64
                },
                "PE": {
                    "B": 1,
                    "S": 16,
                    "P": 16
                },
                "reg_file": {
                    "B": 1,
                    "S": 1,
                    "P": 1
                }
            }
        },
        "FFNT": {
            "tl_rst": {
                "comp_latency": 4.569114144680851,
                "mem_latency": 6.513595581054687e-05,
                "traffic": 2098176,
                "energy": 60108101667.26,
                "traffic_energy": 12039828274829.994,
                "traffic_energy_foreach": {
                    "DRAM": 65463091.199999996,
                    "L3": 11969457504228.094,
                    "reg_file": 70305307510.70209,
                    "traffic": {
                        "DRAM": {
                            "read": 262272.0,
                            "write": 0.0,
                            "update": 0,
                            "leak": 0
                        },
                        "L3": {
                            "read": 618659840.0,
                            "write": 268439554.0,
                            "update": 0,
                            "leak": 0
                        },
                        "reg_file_2d": {
                            "read": 17146314752.0,
                            "write": 17213423616.0,
                            "update": 0,
                            "leak": 0
                        },
                        "reg_file_1d": {
                            "read": 0,
                            "write": 0,
                            "update": 0,
                            "leak": 0
                        }
                    }
                },
                "mac_instances": 256,
                "mac_utilized_instances": 256
            },
            "factors": {
                "DRAM": {
                    "B": 64,
                    "F": 1,
                    "H": 1,
                    "P": 16,
                    "S": 4
                },
                "L3": {
                    "B": 1,
                    "F": 64,
                    "H": 8,
                    "P": 64,
                    "S": 32
                },
                "PE": {
                    "B": 1,
                    "F": 1,
                    "H": 1,
                    "P": 16,
                    "S": 1
                },
                "PE_col": {
                    "B": 1,
                    "F": 1,
                    "H": 1,
                    "P": 1,
                    "S": 16
                },
                "reg_file": {
                    "B": 1,
                    "F": 1,
                    "H": 1,
                    "P": 1,
                    "S": 1
                }
            }
        }
    }
}